yzdb/__init__.py
yzdb/conn_mysql.py
yzdb/conn_sqlite.py
yzdb/db_base.py
yzdb/operations/__init__.py
yzdb/operations/add_mysql.py
yzdb/operations/add_sqlite.py
yzdb/operations/drop_mysql.py
yzdb/operations/drop_sqlite.py
yzdb/operations/modify_mysql.py
yzdb/operations/modify_sqlite.py
yzdb/operations/query_mysql.py
yzdb/operations/query_sqlite.py
YzDB-0.0.3.dist-info/LICENSE
YzDB-0.0.3.dist-info/METADATA
YzDB-0.0.3.dist-info/WHEEL
YzDB-0.0.3.dist-info/top_level.txt
YzDB-0.0.3.dist-info/RECORD
