Metadata-Version: 2.1
Name: YzDB
Version: 0.0.3
Summary: A package for easy using database
Home-page: https://github.com/Yanzhong-Hub/yzdb
Author: Yanzhong Huang
Author-email: yanzhong.huang@outlook.com
License: MIT
Classifier: Programming Language :: Python :: 3
Classifier: License :: OSI Approved :: MIT License
Requires-Python: >=3.10
License-File: LICENSE
Requires-Dist: pandas
Requires-Dist: pymysql
Requires-Dist: cryptography
Requires-Dist: sqlalchemy (>=2.0.0)
Provides-Extra: dev
Requires-Dist: pytest (>=7.0) ; extra == 'dev'
Requires-Dist: twine (>=4.0.2) ; extra == 'dev'
